sentinel_tiles/__init__.py
sentinel_tiles/sentinel2_tiles_world_with_land.geojson
sentinel_tiles/sentinel_tiles.py
sentinel_tiles/version.py
sentinel_tiles-1.1.1.dist-info/licenses/LICENSE
sentinel_tiles-1.1.1.dist-info/METADATA
sentinel_tiles-1.1.1.dist-info/WHEEL
sentinel_tiles-1.1.1.dist-info/top_level.txt
sentinel_tiles-1.1.1.dist-info/RECORD
