Metadata-Version: 2.4
Name: sentinel-tiles
Version: 1.1.1
Summary: generates raster geometries for the Sentinel version of 100km Military Grid Reference System (MGRS) tiles
Author-email: "Gregory H. Halverson" <gregory.h.halverson@jpl.nasa.gov>
Classifier: Programming Language :: Python :: 3
Classifier: Operating System :: OS Independent
Requires-Python: >=3.10
License-File: LICENSE
Requires-Dist: rasters>=1.16.1
Requires-Dist: geopandas
Requires-Dist: mgrs
Requires-Dist: numpy
Requires-Dist: pandas
Requires-Dist: shapely
Requires-Dist: affine
Requires-Dist: python-dateutil
Requires-Dist: sentinelsat
Provides-Extra: dev
Requires-Dist: build; extra == "dev"
Requires-Dist: pytest>=6.0; extra == "dev"
Requires-Dist: pytest-cov; extra == "dev"
Requires-Dist: jupyter; extra == "dev"
Requires-Dist: pytest; extra == "dev"
Requires-Dist: twine; extra == "dev"
Dynamic: license-file
